axe_cli/CHANGELOG.md
axe_cli/__init__.py
axe_cli/acp/AGENTS.md
axe_cli/acp/__init__.py
axe_cli/acp/convert.py
axe_cli/acp/kaos.py
axe_cli/acp/mcp.py
axe_cli/acp/server.py
axe_cli/acp/session.py
axe_cli/acp/tools.py
axe_cli/acp/types.py
axe_cli/agents/default/agent.yaml
axe_cli/agents/default/sub.yaml
axe_cli/agents/default/system.md
axe_cli/agents/okabe/agent.yaml
axe_cli/agentspec.py
axe_cli/app.py
axe_cli/auth/oauth.py
axe_cli/auth/platforms.py
axe_cli/cli/__init__.py
axe_cli/cli/__main__.py
axe_cli/cli/info.py
axe_cli/cli/mcp.py
axe_cli/cli/toad.py
axe_cli/config.py
axe_cli/constant.py
axe_cli/exception.py
axe_cli/llm.py
axe_cli/metadata.py
axe_cli/prompts/__init__.py
axe_cli/prompts/compact.md
axe_cli/prompts/init.md
axe_cli/py.typed
axe_cli/session.py
axe_cli/share.py
axe_cli/skill/__init__.py
axe_cli/skill/flow/__init__.py
axe_cli/skill/flow/d2.py
axe_cli/skill/flow/mermaid.py
axe_cli/skills/axe-cli-help/SKILL.md
axe_cli/skills/skill-creator/SKILL.md
axe_cli/soul/__init__.py
axe_cli/soul/agent.py
axe_cli/soul/approval.py
axe_cli/soul/axesoul.py
axe_cli/soul/compaction.py
axe_cli/soul/context.py
axe_cli/soul/denwarenji.py
axe_cli/soul/message.py
axe_cli/soul/slash.py
axe_cli/soul/toolset.py
axe_cli/token_counter.py
axe_cli/tools/AGENTS.md
axe_cli/tools/__init__.py
axe_cli/tools/axe/__init__.py
axe_cli/tools/axe/auto_init.py
axe_cli/tools/axe/context.py
axe_cli/tools/axe/impact.py
axe_cli/tools/axe/index.py
axe_cli/tools/axe/prewarm.py
axe_cli/tools/axe/search.py
axe_cli/tools/axe/structure.py
axe_cli/tools/axe/warm.py
axe_cli/tools/display.py
axe_cli/tools/dmail/__init__.py
axe_cli/tools/dmail/dmail.md
axe_cli/tools/file/__init__.py
axe_cli/tools/file/glob.md
axe_cli/tools/file/glob.py
axe_cli/tools/file/grep.md
axe_cli/tools/file/grep_local.py
axe_cli/tools/file/read.md
axe_cli/tools/file/read.py
axe_cli/tools/file/read_media.md
axe_cli/tools/file/read_media.py
axe_cli/tools/file/replace.md
axe_cli/tools/file/replace.py
axe_cli/tools/file/utils.py
axe_cli-1.7.6.dist-info/WHEEL
axe_cli-1.7.6.dist-info/entry_points.txt
axe_cli-1.7.6.dist-info/METADATA
axe_cli-1.7.6.dist-info/RECORD
